[
  {
    "id": 1,
    "name": "Auntie's",
    "slug": "aunties",
    "description": "",
    "website": "https://auntiesbooks.com/",
    "job_board_url": "",
    "logo_url": "https://auntiesbooks.com/sites/default/files/styles/logo/public/2024-06/auntieslogoforwebsite30.png",
    "industry": "",
    "created_at": "2025-06-13 13:50:00+00",
    "updated_at": "2025-06-13 13:50:00+00"
  },
  {
    "id": 2,
    "name": "Avista",
    "slug": "avista",
    "description": "",
    "website": "https://www.myavista.com/",
    "job_board_url": "https://recruiting2.ultipro.com/AVI1000AMAST/JobBoard/362abf68-95c3-4b17-a39d-76a6efe5ff18/?q=&o=postedDateDesc&f4=ITpN1FEJvlWudZe0AayqWA",
    "logo_url": "https://www.myavista.com/areas/myavista/assets/dist/img/content/avista_logo.svg",
    "industry": "",
    "created_at": "2025-06-13 13:50:00+00",
    "updated_at": "2025-06-13 13:50:00+00"
  },
  {
    "id": 3,
    "name": "Bluestone Apps",
    "slug": "bluestone_apps",
    "description": "",
    "website": "https://bluestoneapps.com/mobile-app-developers-spokane-wa/",
    "job_board_url": "",
    "logo_url": "https://bluestoneapps.com/wp-content/uploads/2020/10/bluestone-apps-logo-header.png",
    "industry": "",
    "created_at": "2025-06-13 13:50:00+00",
    "updated_at": "2025-06-13 13:50:00+00"
  },
  {
    "id": 4,
    "name": "CDL PowerSuite",
    "slug": "cdl_powersuite",
    "description": "",
    "website": "https://www.cdlpowersuite.com/",
    "job_board_url": "",
    "logo_url": "https://irp.cdn-website.com/1b2aebf3/dms3rep/multi/CDL+PowerSuite+Logo+Landscape+%281%29.png",
    "industry": "",
    "created_at": "2025-06-13 13:50:00+00",
    "updated_at": "2025-06-13 13:50:00+00"
  },
  {
    "id": 5,
    "name": "Central Valley School District",
    "slug": "cvsd",
    "description": "",
    "website": "https://www.cvsd.org/",
    "job_board_url": "https://jobs.redroverk12.com/org/cvsd",
    "logo_url": "https://3.files.edl.io/fde9/22/10/31/223600-2fb1586e-7561-4b23-a4af-f74b3bbc3ab1.png",
    "industry": "",
    "created_at": "2025-06-13 13:50:00+00",
    "updated_at": "2025-06-13 13:50:00+00"
  },
  {
    "id": 6,
    "name": "City Of Spokane",
    "slug": "city_of_spokane",
    "description": "",
    "website": "https://my.spokanecity.org/",
    "job_board_url": "https://www.governmentjobs.com/careers/spokanecity",
    "logo_url": "https://static.spokanecity.org/my/svg/pavilion-clock-tower-bridge.svg",
    "industry": "",
    "created_at": "2025-06-13 13:50:00+00",
    "updated_at": "2025-06-13 13:50:00+00"
  },
  {
    "id": 7,
    "name": "CloudEngage",
    "slug": "cloudengage",
    "description": "",
    "website": "https://cloudengage.com/",
    "job_board_url": "",
    "logo_url": "https://cloudengage.com/wp-content/uploads/2021/07/ce-logo-blue-1.png",
    "industry": "",
    "created_at": "2025-06-13 13:50:00+00",
    "updated_at": "2025-06-13 13:50:00+00"
  },
  {
    "id": 8,
    "name": "Codespeed",
    "slug": "codespeed",
    "description": "",
    "website": "https://www.codespeed.com",
    "job_board_url": "https://www.codespeed.com/careers",
    "logo_url": "",
    "industry": "",
    "created_at": "2025-06-13 13:50:00+00",
    "updated_at": "2025-06-13 13:50:00+00"
  },
  {
    "id": 9,
    "name": "Collabra Technology Inc",
    "slug": "collabra",
    "description": "",
    "website": "https://www.collabratechnology.com",
    "job_board_url": "",
    "logo_url": "https://collabera.com/wp-content/uploads/2025/03/Group-1597883429.png",
    "industry": "",
    "created_at": "2025-06-13 13:50:00+00",
    "updated_at": "2025-06-13 13:50:00+00"
  },
  {
    "id": 10,
    "name": "Critical Logic Inc",
    "slug": "critical-logic",
    "description": "",
    "website": "https://critical-logic.com/",
    "job_board_url": "",
    "logo_url": "",
    "industry": "",
    "created_at": "2025-06-13 13:50:00+00",
    "updated_at": "2025-06-13 13:50:00+00"
  },
  {
    "id": 11,
    "name": "Drip 7",
    "slug": "drip_7",
    "description": "",
    "website": "https://drip7.com/",
    "job_board_url": "",
    "logo_url": "https://drip7.com/wp-content/uploads/2023/10/drip7-logo-R-light-blue-300x163-1.png",
    "industry": "",
    "created_at": "2025-06-13 13:50:00+00",
    "updated_at": "2025-06-13 13:50:00+00"
  },
  {
    "id": 12,
    "name": "Egnyte",
    "slug": "egnyte",
    "description": "",
    "website": "https://www.egnyte.com/",
    "job_board_url": "https://jobs.jobvite.com/egnyte/jobs",
    "logo_url": "https://www.egnyte.com/themes/custom/egnyte/logo.svg",
    "industry": "",
    "created_at": "2025-06-13 13:50:00+00",
    "updated_at": "2025-06-13 13:50:00+00"
  },
  {
    "id": 13,
    "name": "Enhanced Software Products",
    "slug": "enhanced_software_products",
    "description": "",
    "website": "https://www.espsolution.net/",
    "job_board_url": "https://www.espsolution.net/careers",
    "logo_url": "",
    "industry": "",
    "created_at": "2025-06-13 13:50:00+00",
    "updated_at": "2025-06-13 13:50:00+00"
  },
  {
    "id": 14,
    "name": "F5",
    "slug": "f5",
    "description": "",
    "website": "https://www.f5.com/",
    "job_board_url": "https://ffive.wd5.myworkdayjobs.com/en-US/f5jobs?locations=7a119632acd0109fda3ee06f7c2b4bbe",
    "logo_url": "https://www.f5.com/content/dam/f5/f5-logo.svg",
    "industry": "",
    "created_at": "2025-06-13 13:50:00+00",
    "updated_at": "2025-06-13 13:50:00+00"
  },
  {
    "id": 15,
    "name": "Gestalt Diagnostics",
    "slug": "gestalt_diagnostics",
    "description": "",
    "website": "https://www.gestaltdiagnostics.com/",
    "job_board_url": "https://www.gestaltdiagnostics.com/careers",
    "logo_url": "https://lirp.cdn-website.com/6f2d1a4f/dms3rep/multi/opt/893X250+72dpi-326w.png",
    "industry": "",
    "created_at": "2025-06-13 13:50:00+00",
    "updated_at": "2025-06-13 13:50:00+00"
  },
  {
    "id": 16,
    "name": "Gravity Jack",
    "slug": "gravity_jack",
    "description": "",
    "website": "https://www.gravityjack.com/",
    "job_board_url": "https://careers.smartrecruiters.com/GravityJack",
    "logo_url": "https://www.gravityjack.com/wp-content/uploads/2023/09/big_logo_single.png",
    "industry": "",
    "created_at": "2025-06-13 13:50:00+00",
    "updated_at": "2025-06-13 13:50:00+00"
  },
  {
    "id": 17,
    "name": "Houdini Interactive",
    "slug": "houdini_interactive",
    "description": "",
    "website": "https://www.houdini.studio/",
    "job_board_url": "",
    "logo_url": "https://www.houdini.studio/wp-content/uploads/2022/07/logo-houdini-full-pink.png",
    "industry": "",
    "created_at": "2025-06-13 13:50:00+00",
    "updated_at": "2025-06-13 13:50:00+00"
  },
  {
    "id": 18,
    "name": "Huntwood Custom Cabinets",
    "slug": "huntwood",
    "description": "",
    "website": "https://www.huntwood.com/",
    "job_board_url": "https://www.huntwood.com/employment-opportunities/",
    "logo_url": "https://www.huntwood.com/wp-content/uploads/2020/06/HuntwoodCustomCabinets-e1592503657987.png",
    "industry": "",
    "created_at": "2025-06-13 13:50:00+00",
    "updated_at": "2025-06-13 13:50:00+00"
  },
  {
    "id": 19,
    "name": "IntelliTect",
    "slug": "intellitect",
    "description": "",
    "website": "https://intellitect.com/",
    "job_board_url": "https://intellitect.com/about/careers/#open-jobs",
    "logo_url": "https://intellitect.com/wp-content/uploads/2021/10/IntelliTect-Logo-Secondary-BlueWhite-300x64-1.png",
    "industry": "",
    "created_at": "2025-06-13 13:50:00+00",
    "updated_at": "2025-06-13 13:50:00+00"
  },
  {
    "id": 20,
    "name": "Itron",
    "slug": "itron",
    "description": "",
    "website": "https://na.itron.com/",
    "job_board_url": "https://itron.wd5.myworkdayjobs.com/Itron",
    "logo_url": "https://na.itron.com/documents/44645/153007/ItronLogo24.svg/8ba06c71-1e5e-5647-8322-20466e9f3e41",
    "industry": "",
    "created_at": "2025-06-13 13:50:00+00",
    "updated_at": "2025-06-13 13:50:00+00"
  },
  {
    "id": 21,
    "name": "Jax Consulting",
    "slug": "jax_consulting",
    "description": "",
    "website": "https://www.jaxconsult.com/",
    "job_board_url": "",
    "logo_url": "",
    "industry": "",
    "created_at": "2025-06-13 13:50:00+00",
    "updated_at": "2025-06-13 13:50:00+00"
  },
  {
    "id": 22,
    "name": "Kaiser Aluminum",
    "slug": "kaiser_aluminum",
    "description": "",
    "website": "https://www.kaiseraluminum.com/",
    "job_board_url": "https://myjobs.adp.com/kaisercareers/cx/job-listing",
    "logo_url": "https://www.kaiseraluminum.com/wp-content/themes/worksdesign/img/logo.png",
    "industry": "",
    "created_at": "2025-06-13 13:50:00+00",
    "updated_at": "2025-06-13 13:50:00+00"
  },
  {
    "id": 23,
    "name": "Leading Edge Software",
    "slug": "leading_edge_software",
    "description": "",
    "website": "http://www.ledgesoft.com/",
    "job_board_url": "",
    "logo_url": "",
    "industry": "",
    "created_at": "2025-06-13 13:50:00+00",
    "updated_at": "2025-06-13 13:50:00+00"
  },
  {
    "id": 24,
    "name": "Limelyte Technology Group Inc",
    "slug": "limelyte",
    "description": "",
    "website": "https://www.limelyte.com/",
    "job_board_url": "https://apply.workable.com/limelyte-technology-group/",
    "logo_url": "https://cdn.prod.website-files.com/62d471d6aa648f1fd9176ab7/62d4743c817b0575c0c9b938_logo.svg",
    "industry": "",
    "created_at": "2025-06-13 13:50:00+00",
    "updated_at": "2025-06-13 13:50:00+00"
  },
  {
    "id": 26,
    "name": "MLC CAD Systems",
    "slug": "mlc_cad_systems",
    "description": "",
    "website": "https://www.mlc-cad.com/",
    "job_board_url": "",
    "logo_url": "",
    "industry": "",
    "created_at": "2025-06-13 13:50:00+00",
    "updated_at": "2025-06-13 13:50:00+00"
  },
  {
    "id": 27,
    "name": "MODE Workspaces",
    "slug": "mode_workspaces",
    "description": "",
    "website": "https://www.findyourmode.com/",
    "job_board_url": "",
    "logo_url": "https://images.squarespace-cdn.com/content/v1/6747ddded70049288904681c/54942270-fbaa-4956-8a8e-6c6640034509/mode_lifestyle_campus_header_logo.png",
    "industry": "",
    "created_at": "2025-06-13 13:50:00+00",
    "updated_at": "2025-06-13 13:50:00+00"
  },
  {
    "id": 28,
    "name": "Numerica",
    "slug": "numerica",
    "description": "",
    "website": "https://www.numericacu.com/",
    "job_board_url": "https://recruiting.paylocity.com/recruiting/jobs/All/3e0b08f9-66f1-4617-9a26-159571b53dc2/Numerica-Credit-Union",
    "logo_url": "https://www.numericacu.com/assets/numericacu-logo.svg",
    "industry": "",
    "created_at": "2025-06-13 13:50:00+00",
    "updated_at": "2025-06-13 13:50:00+00"
  },
  {
    "id": 29,
    "name": "Nyvara Software",
    "slug": "nyvara_software",
    "description": "",
    "website": "https://nyvara.software/",
    "job_board_url": "",
    "logo_url": "",
    "industry": "",
    "created_at": "2025-06-13 13:50:00+00",
    "updated_at": "2025-06-13 13:50:00+00"
  },
  {
    "id": 30,
    "name": "OpenEye",
    "slug": "openeye",
    "description": "",
    "website": "https://openeye.net/",
    "job_board_url": "https://job-boards.greenhouse.io/openeye",
    "logo_url": "https://www.openeye.net/wp-content/uploads/2023/04/logo.png",
    "industry": "",
    "created_at": "2025-06-13 13:50:00+00",
    "updated_at": "2025-06-13 13:50:00+00"
  },
  {
    "id": 31,
    "name": "Page 42 Bookstore",
    "slug": "page_42_bookstore",
    "description": "",
    "website": "https://www.page42bookstore.com/",
    "job_board_url": "",
    "logo_url": "",
    "industry": "",
    "created_at": "2025-06-13 13:50:00+00",
    "updated_at": "2025-06-13 13:50:00+00"
  },
  {
    "id": 32,
    "name": "Paradise Fibers",
    "slug": "paradise_fibers",
    "description": "",
    "website": "https://paradisefibers.com/",
    "job_board_url": "",
    "logo_url": "",
    "industry": "",
    "created_at": "2025-06-13 13:50:00+00",
    "updated_at": "2025-06-13 13:50:00+00"
  },
  {
    "id": 33,
    "name": "PayTrace Inc",
    "slug": "paytrace",
    "description": "",
    "website": "https://paytrace.net/",
    "job_board_url": "https://nabancard.wd1.myworkdayjobs.com/nab",
    "logo_url": "",
    "industry": "",
    "created_at": "2025-06-13 13:50:00+00",
    "updated_at": "2025-06-13 13:50:00+00"
  },
  {
    "id": 34,
    "name": "Providence",
    "slug": "providence",
    "description": "",
    "website": "https://www.providence.org/locations/wa/sacred-heart-medical-center",
    "job_board_url": "https://providence-spokane.jobs/",
    "logo_url": "",
    "industry": "",
    "created_at": "2025-06-13 13:50:00+00",
    "updated_at": "2025-06-13 13:50:00+00"
  },
  {
    "id": 35,
    "name": "RiskLens",
    "slug": "risklens",
    "description": "",
    "website": "https://www.risklens.com/",
    "job_board_url": "https://jobs.lever.co/safe/",
    "logo_url": "",
    "industry": "",
    "created_at": "2025-06-13 13:50:00+00",
    "updated_at": "2025-06-13 13:50:00+00"
  },
  {
    "id": 36,
    "name": "Schweitzer Engineering Laboratories",
    "slug": "sel",
    "description": "",
    "website": "https://selinc.com/",
    "job_board_url": "https://selinc.wd1.myworkdayjobs.com/SEL/20/refreshFacet/318c8bb6f553100021d223d9780d30be",
    "logo_url": "",
    "industry": "",
    "created_at": "2025-06-13 13:50:00+00",
    "updated_at": "2025-06-13 13:50:00+00"
  },
  {
    "id": 37,
    "name": "SkillTRAN LLC",
    "slug": "skilltran",
    "description": "",
    "website": "https://skilltran.com/",
    "job_board_url": "",
    "logo_url": "",
    "industry": "",
    "created_at": "2025-06-13 13:50:00+00",
    "updated_at": "2025-06-13 13:50:00+00"
  },
  {
    "id": 38,
    "name": "Softechnologies",
    "slug": "softechnologies",
    "description": "",
    "website": "https://softechnologies.com/",
    "job_board_url": "",
    "logo_url": "",
    "industry": "",
    "created_at": "2025-06-13 13:50:00+00",
    "updated_at": "2025-06-13 13:50:00+00"
  },
  {
    "id": 40,
    "name": "Spokane Computer Inc",
    "slug": "spokane_computer",
    "description": "",
    "website": "https://www.spokanecomputer.com/",
    "job_board_url": "https://www.spokanecomputer.com/Careers",
    "logo_url": "",
    "industry": "",
    "created_at": "2025-06-13 13:50:00+00",
    "updated_at": "2025-06-13 13:50:00+00"
  },
  {
    "id": 41,
    "name": "Spokane County Library",
    "slug": "scld",
    "description": "",
    "website": "https://www.scld.org/",
    "job_board_url": "https://scld.agilehr.com/careers/",
    "logo_url": "",
    "industry": "",
    "created_at": "2025-06-13 13:50:00+00",
    "updated_at": "2025-06-13 13:50:00+00"
  },
  {
    "id": 42,
    "name": "Spokane Public Library",
    "slug": "spokane_library",
    "description": "",
    "website": "https://www.spokanelibrary.org/",
    "job_board_url": "https://spokanelibrary.org/employment/",
    "logo_url": "",
    "industry": "",
    "created_at": "2025-06-13 13:50:00+00",
    "updated_at": "2025-06-13 13:50:00+00"
  },
  {
    "id": 43,
    "name": "Spokane Public Schools",
    "slug": "sps",
    "description": "",
    "website": "https://www.spokaneschools.org/",
    "job_board_url": "https://www.schooljobs.com/careers/spokaneschools",
    "logo_url": "",
    "industry": "",
    "created_at": "2025-06-13 13:50:00+00",
    "updated_at": "2025-06-13 13:50:00+00"
  },
  {
    "id": 44,
    "name": "Spokane Software Systems Inc",
    "slug": "spokane_software_systems",
    "description": "",
    "website": "http://www.spokane.ag/",
    "job_board_url": "",
    "logo_url": "",
    "industry": "",
    "created_at": "2025-06-13 13:50:00+00",
    "updated_at": "2025-06-13 13:50:00+00"
  },
  {
    "id": 45,
    "name": "StaffReady",
    "slug": "staffready",
    "description": "",
    "website": "https://staffready.com/",
    "job_board_url": "",
    "logo_url": "",
    "industry": "",
    "created_at": "2025-06-13 13:50:00+00",
    "updated_at": "2025-06-13 13:50:00+00"
  },
  {
    "id": 46,
    "name": "STCU",
    "slug": "stcu",
    "description": "",
    "website": "https://stcu.org/",
    "job_board_url": "https://careers.smartrecruiters.com/STCU1",
    "logo_url": "",
    "industry": "",
    "created_at": "2025-06-13 13:50:00+00",
    "updated_at": "2025-06-13 13:50:00+00"
  },
  {
    "id": 47,
    "name": "SynergisticIT",
    "slug": "synergisticit",
    "description": "",
    "website": "https://www.synergisticit.com/",
    "job_board_url": "https://www1.jobdiva.com/portal/?a=ygjdnwl6apzmff6t82vdutfvbydrtq07d9es5jck4la1ce7huuaom4zlm4i0c94q&compid=0#/",
    "logo_url": "",
    "industry": "",
    "created_at": "2025-06-13 13:50:00+00",
    "updated_at": "2025-06-13 13:50:00+00"
  },
  {
    "id": 48,
    "name": "Tamarack Software Inc",
    "slug": "tamarack_software",
    "description": "",
    "website": "https://www.tamarack-software.com/",
    "job_board_url": "",
    "logo_url": "",
    "industry": "",
    "created_at": "2025-06-13 13:50:00+00",
    "updated_at": "2025-06-13 13:50:00+00"
  },
  {
    "id": 49,
    "name": "Target System Tech",
    "slug": "target_system_tech",
    "description": "",
    "website": "https://target-sys-tech.com/",
    "job_board_url": "",
    "logo_url": "",
    "industry": "",
    "created_at": "2025-06-13 13:50:00+00",
    "updated_at": "2025-06-13 13:50:00+00"
  },
  {
    "id": 50,
    "name": "Treasury4",
    "slug": "treasury4",
    "description": "",
    "website": "https://www.treasury4.com/",
    "job_board_url": "https://www.linkedin.com/company/treasury4/jobs/",
    "logo_url": "",
    "industry": "",
    "created_at": "2025-06-13 13:50:00+00",
    "updated_at": "2025-06-13 13:50:00+00"
  },
  {
    "id": 51,
    "name": "Two Barrels LLC",
    "slug": "two_barrels",
    "description": "",
    "website": "https://www.twobarrels.com/",
    "job_board_url": "https://www.twobarrels.com/jobs/",
    "logo_url": "",
    "industry": "",
    "created_at": "2025-06-13 13:50:00+00",
    "updated_at": "2025-06-13 13:50:00+00"
  },
  {
    "id": 52,
    "name": "URM",
    "slug": "urm",
    "description": "",
    "website": "https://www.urmstores.com/",
    "job_board_url": "https://recruiting.paylocity.com/recruiting/jobs/All/6650dbeb-608a-4cef-a3a3-c10e3a6291cd/URM-Stores-Inc",
    "logo_url": "",
    "industry": "",
    "created_at": "2025-06-13 13:50:00+00",
    "updated_at": "2025-06-13 13:50:00+00"
  },
  {
    "id": 53,
    "name": "Wagstaff",
    "slug": "wagstaff",
    "description": "",
    "website": "https://wagstaffat.com/",
    "job_board_url": "https://recruiting.paylocity.com/Recruiting/Jobs/All/922a365c-e2f9-4a44-a008-88fdfcd0f0ac/Wagstaff-Inc",
    "logo_url": "",
    "industry": "",
    "created_at": "2025-06-13 13:50:00+00",
    "updated_at": "2025-06-13 13:50:00+00"
  },
  {
    "id": 55,
    "name": "WinCo",
    "slug": "winco",
    "description": "",
    "website": "https://www.wincofoods.com/",
    "job_board_url": "https://careers-winco.icims.com/jobs/intro",
    "logo_url": "",
    "industry": "",
    "created_at": "2025-06-13 13:50:00+00",
    "updated_at": "2025-06-13 13:50:00+00"
  }
]